pydream/Dream.py
pydream/Dream_shared_vars.py
pydream/__init__.py
pydream/convergence.py
pydream/core.py
pydream/model.py
pydream/parameters.py
pydream/examples/corm/exp_data/exp_data_pg.txt
pydream/examples/corm/exp_data/exp_data_pgg.txt
pydream/examples/corm/exp_data/exp_data_sd_pg.txt
pydream/examples/corm/exp_data/exp_data_sd_pgg.txt
pydream/examples/robertson/exp_data/exp_data_ctotal.txt
pydream/examples/robertson/exp_data/exp_data_sd_ctotal.txt
pydream-2.0.0.dist-info/LICENSE
pydream-2.0.0.dist-info/METADATA
pydream-2.0.0.dist-info/WHEEL
pydream-2.0.0.dist-info/top_level.txt
pydream-2.0.0.dist-info/RECORD
