Metadata-Version: 2.1
Name: pydream
Version: 2.0.0
Summary: A Python implementation of the MT-DREAM(ZS) algorithm from Laloy and Vrugt 2012.
Home-page: https://github.com/LoLab-VU/PyDREAM
Author: Erin Shockley
Author-email: erin.shockley@vanderbilt.edu
License: UNKNOWN
Platform: UNKNOWN
Classifier: Programming Language :: Python :: 3
Requires-Dist: numpy
Requires-Dist: scipy
